carm/__init__.py
carm/carm.py
carm/carm_dds.py
carm/carm_ros2.py
carm-0.1.20251017.dist-info/METADATA
carm-0.1.20251017.dist-info/WHEEL
carm-0.1.20251017.dist-info/entry_points.txt
carm-0.1.20251017.dist-info/top_level.txt
carm-0.1.20251017.dist-info/RECORD
