Metadata-Version: 2.1
Name: carm
Version: 0.1.20251017
Summary: Python interface for cvte arm.
Author-email: Yong Zhao <zhaoyong11933@cvte.com>
Classifier: Programming Language :: Python :: 3
Classifier: Programming Language :: Python :: Implementation :: CPython
Classifier: Programming Language :: Python :: Implementation :: PyPy
Requires-Python: >=3.6
Requires-Dist: websocket-client
